tatumpython/__init__.py
tatumpython/test.py
tatumpython/tatum/__init__.py
tatumpython/tatum/blockchain/__init__.py
tatumpython/tatum/blockchain/bitcoin.py
tatumpython/tatum/blockchain/bitcoin_cash.py
tatumpython/tatum/blockchain/ethereum.py
tatumpython/tatum/blockchain/litecoin.py
tatumpython/tatum/blockchain/xlm.py
tatumpython/tatum/blockchain/xrp.py
tatumpython/tatum/ledger/__init__.py
tatumpython/tatum/ledger/account.py
tatumpython/tatum/ledger/customer.py
tatumpython/tatum/ledger/order_book.py
tatumpython/tatum/ledger/subscription.py
tatumpython/tatum/ledger/transaction.py
tatumpython/tatum/ledger/virtual_currency.py
tatumpython/tatum/offchain/__init__.py
tatumpython/tatum/offchain/account.py
tatumpython/tatum/offchain/blockchain.py
tatumpython/tatum/offchain/withdrawal.py
tatumpython/tatum/security/__init__.py
tatumpython/tatum/security/address.py
tatumpython/tatum/security/key_management_system.py
tatumpython/validator/__init__.py
tatumpython/validator/blockchain.py
tatumpython/validator/ledger.py
tatumpython/validator/offchain.py
tatumpython/validator/security.py
tatumpython-1.0.0.dist-info/LICENSE.txt
tatumpython-1.0.0.dist-info/METADATA
tatumpython-1.0.0.dist-info/WHEEL
tatumpython-1.0.0.dist-info/top_level.txt
tatumpython-1.0.0.dist-info/RECORD
